Augmentext/FeatureExtraction.py
Augmentext/Global.py
Augmentext/MedRegEx.py
Augmentext/Normalisations.py
Augmentext/Operations.py
Augmentext/Pipeline.py
Augmentext/TextOperations.py
Augmentext/__init__.py
Augmentext-0.1.7.dist-info/LICENSE
Augmentext-0.1.7.dist-info/METADATA
Augmentext-0.1.7.dist-info/WHEEL
Augmentext-0.1.7.dist-info/top_level.txt
Augmentext-0.1.7.dist-info/RECORD
